Strive
