Metadata-Version: 2.1
Name: Strive
Version: 0.0.6
Summary: Make use of Tkinter in XML.
Home-page: https://bruhdev.com
Author: BruhDev
Author-email: mr.bruh.dev@gmail.com
License: UNKNOWN
Platform: UNKNOWN
Requires-Python: >=3.7
